pub_guard_llm/__init__.py
pub_guard_llm/model/__init__.py
pub_guard_llm/model/inference.py
pub_guard_llm/model/utils.py
pub_guard_llm/model/data/affiliation_cache.jsonl
pub_guard_llm/model/data/journal_cache.jsonl
pub_guard_llm/test/__init__.py
pub_guard_llm/test/utils_test.py
pub_guard_llm-0.0.5.dist-info/METADATA
pub_guard_llm-0.0.5.dist-info/WHEEL
pub_guard_llm-0.0.5.dist-info/licenses/LICENSE
pub_guard_llm-0.0.5.dist-info/RECORD
