Metadata-Version: 2.4
Name: pub_guard_llm
Version: 0.0.5
Summary: A pipeline to detect fraudulent articles
License-File: LICENSE
